xer_reader/__init__.py
xer_reader/src/reader.py
xer_reader/src/table.py
xer_reader/src/table_data.py
xer_reader-0.4.1.dist-info/LICENSE
xer_reader-0.4.1.dist-info/METADATA
xer_reader-0.4.1.dist-info/WHEEL
xer_reader-0.4.1.dist-info/entry_points.txt
xer_reader-0.4.1.dist-info/RECORD
