Metadata-Version: 2.1
Name: xer-reader
Version: 0.4.1
Summary: Read and parse a Primavera P6 xer file.
Home-page: https://github.com/jjCode01/xer-reader
License: GPL-3.0-only
Keywords: primavera,p6,xer,schedule,scheduling,planning,project management,project controls
Author: Jesse Jones
Author-email: code@seqmanagement.com
Requires-Python: >=3.10,<4.0
Classifier: License :: OSI Approved :: GNU General Public License v3 (GPLv3)
Classifier: Programming Language :: Python :: 3
Classifier: Programming Language :: Python :: 3.10
Classifier: Programming Language :: Python :: 3.11
Classifier: Programming Language :: Python :: 3.12
Classifier: Programming Language :: Python :: 3.13
Requires-Dist: openpyxl (>=3.1.2,<4.0.0)
Project-URL: Repository, https://github.com/jjCode01/xer-reader
